{"nodes": [{"id": "repository", "label": "repository.py", "file_type": "code", "source_file": "src/apps/event/repository.py", "source_location": "L1"}, {"id": "repository_eventrepository", "label": "EventRepository", "file_type": "code", "source_file": "src/apps/event/repository.py", "source_location": "L14"}, {"id": "repository_eventrepository_init", "label": ".__init__()", "file_type": "code", "source_file": "src/apps/event/repository.py", "source_location": "L15"}, {"id": "repository_session", "label": "session()", "file_type": "code", "source_file": "src/apps/event/repository.py", "source_location": "L19"}, {"id": "repository_eventrepository_add", "label": ".add()", "file_type": "code", "source_file": "src/apps/event/repository.py", "source_location": "L22"}, {"id": "repository_eventrepository_get_by_id_for_owner", "label": ".get_by_id_for_owner()", "file_type": "code", "source_file": "src/apps/event/repository.py", "source_location": "L25"}, {"id": "repository_eventrepository_get_by_id", "label": ".get_by_id()", "file_type": "code", "source_file": "src/apps/event/repository.py", "source_location": "L37"}, {"id": "repository_eventrepository_get_by_id_for_update", "label": ".get_by_id_for_update()", "file_type": "code", "source_file": "src/apps/event/repository.py", "source_location": "L42"}, {"id": "repository_eventrepository_create_event_day", "label": ".create_event_day()", "file_type": "code", "source_file": "src/apps/event/repository.py", "source_location": "L47"}, {"id": "repository_eventrepository_get_event_day_for_owner", "label": ".get_event_day_for_owner()", "file_type": "code", "source_file": "src/apps/event/repository.py", "source_location": "L74"}, {"id": "repository_eventrepository_get_event_day_by_id", "label": ".get_event_day_by_id()", "file_type": "code", "source_file": "src/apps/event/repository.py", "source_location": "L87"}, {"id": "repository_eventrepository_list_event_days", "label": ".list_event_days()", "file_type": "code", "source_file": "src/apps/event/repository.py", "source_location": "L93"}, {"id": "repository_eventrepository_delete_event_day", "label": ".delete_event_day()", "file_type": "code", "source_file": "src/apps/event/repository.py", "source_location": "L101"}, {"id": "repository_eventrepository_count_event_days", "label": ".count_event_days()", "file_type": "code", "source_file": "src/apps/event/repository.py", "source_location": "L111"}, {"id": "repository_eventrepository_count_ticket_types", "label": ".count_ticket_types()", "file_type": "code", "source_file": "src/apps/event/repository.py", "source_location": "L116"}, {"id": "repository_eventrepository_count_ticket_allocations", "label": ".count_ticket_allocations()", "file_type": "code", "source_file": "src/apps/event/repository.py", "source_location": "L121"}, {"id": "repository_eventrepository_list_ticket_types", "label": ".list_ticket_types()", "file_type": "code", "source_file": "src/apps/event/repository.py", "source_location": "L128"}, {"id": "repository_eventrepository_list_allocations", "label": ".list_allocations()", "file_type": "code", "source_file": "src/apps/event/repository.py", "source_location": "L136"}, {"id": "repository_eventrepository_create_scan_status_history", "label": ".create_scan_status_history()", "file_type": "code", "source_file": "src/apps/event/repository.py", "source_location": "L145"}, {"id": "repository_eventrepository_list_scan_status_history", "label": ".list_scan_status_history()", "file_type": "code", "source_file": "src/apps/event/repository.py", "source_location": "L165"}, {"id": "repository_eventrepository_list_media_assets", "label": ".list_media_assets()", "file_type": "code", "source_file": "src/apps/event/repository.py", "source_location": "L175"}, {"id": "repository_eventrepository_get_media_asset_by_id", "label": ".get_media_asset_by_id()", "file_type": "code", "source_file": "src/apps/event/repository.py", "source_location": "L193"}, {"id": "repository_eventrepository_delete_media_asset", "label": ".delete_media_asset()", "file_type": "code", "source_file": "src/apps/event/repository.py", "source_location": "L199"}, {"id": "repository_eventrepository_get_interest_for_actor", "label": ".get_interest_for_actor()", "file_type": "code", "source_file": "src/apps/event/repository.py", "source_location": "L204"}, {"id": "repository_eventrepository_create_event_interest", "label": ".create_event_interest()", "file_type": "code", "source_file": "src/apps/event/repository.py", "source_location": "L217"}, {"id": "repository_eventrepository_increment_event_interest_counter", "label": ".increment_event_interest_counter()", "file_type": "code", "source_file": "src/apps/event/repository.py", "source_location": "L237"}, {"id": "repository_eventrepository_create_event_reseller", "label": ".create_event_reseller()", "file_type": "code", "source_file": "src/apps/event/repository.py", "source_location": "L244"}, {"id": "repository_eventrepository_get_reseller_for_event", "label": ".get_reseller_for_event()", "file_type": "code", "source_file": "src/apps/event/repository.py", "source_location": "L264"}, {"id": "repository_eventrepository_list_resellers_for_event", "label": ".list_resellers_for_event()", "file_type": "code", "source_file": "src/apps/event/repository.py", "source_location": "L276"}, {"id": "repository_eventrepository_list_reseller_invites_for_event", "label": ".list_reseller_invites_for_event()", "file_type": "code", "source_file": "src/apps/event/repository.py", "source_location": "L284"}, {"id": "repository_eventrepository_list_published_events", "label": ".list_published_events()", "file_type": "code", "source_file": "src/apps/event/repository.py", "source_location": "L307"}, {"id": "repository_rationale_88", "label": "Get an event day by ID without ownership check.", "file_type": "rationale", "source_file": "src/apps/event/repository.py", "source_location": "L88"}, {"id": "repository_rationale_178", "label": "List media assets for event, optionally filtered by type.", "file_type": "rationale", "source_file": "src/apps/event/repository.py", "source_location": "L178"}, {"id": "repository_rationale_194", "label": "Get media asset by ID.", "file_type": "rationale", "source_file": "src/apps/event/repository.py", "source_location": "L194"}, {"id": "repository_rationale_200", "label": "Delete media asset from database.", "file_type": "rationale", "source_file": "src/apps/event/repository.py", "source_location": "L200"}, {"id": "repository_rationale_291", "label": "List invites for an event, optionally filtered by status.", "file_type": "rationale", "source_file": "src/apps/event/repository.py", "source_location": "L291"}], "edges": [{"source": "repository", "target": "typing", "relation": "imports_from", "confidence": "EXTRACTED", "source_file": "src/apps/event/repository.py", "source_location": "L1", "weight": 1.0}, {"source": "repository", "target": "uuid", "relation": "imports_from", "confidence": "EXTRACTED", "source_file": "src/apps/event/repository.py", "source_location": "L2", "weight": 1.0}, {"source": "repository", "target": "sqlalchemy", "relation": "imports_from", "confidence": "EXTRACTED", "source_file": "src/apps/event/repository.py", "source_location": "L4", "weight": 1.0}, {"source": "repository", "target": "sqlalchemy_ext_asyncio", "relation": "imports_from", "confidence": "EXTRACTED", "source_file": "src/apps/event/repository.py", "source_location": "L5", "weight": 1.0}, {"source": "repository", "target": "apps_organizer_models", "relation": "imports_from", "confidence": "EXTRACTED", "source_file": "src/apps/event/repository.py", "source_location": "L7", "weight": 1.0}, {"source": "repository", "target": "apps_ticketing_models", "relation": "imports_from", "confidence": "EXTRACTED", "source_file": "src/apps/event/repository.py", "source_location": "L8", "weight": 1.0}, {"source": "repository", "target": "apps_user_invite_models", "relation": "imports_from", "confidence": "EXTRACTED", "source_file": "src/apps/event/repository.py", "source_location": "L9", "weight": 1.0}, {"source": "repository", "target": "models", "relation": "imports_from", "confidence": "EXTRACTED", "source_file": "src/apps/event/repository.py", "source_location": "L11", "weight": 1.0}, {"source": "repository", "target": "repository_eventrepository", "relation": "contains", "confidence": "EXTRACTED", "source_file": "src/apps/event/repository.py", "source_location": "L14", "weight": 1.0}, {"source": "repository_eventrepository", "target": "repository_eventrepository_init", "relation": "method", "confidence": "EXTRACTED", "source_file": "src/apps/event/repository.py", "source_location": "L15", "weight": 1.0}, {"source": "repository", "target": "repository_session", "relation": "contains", "confidence": "EXTRACTED", "source_file": "src/apps/event/repository.py", "source_location": "L19", "weight": 1.0}, {"source": "repository_eventrepository", "target": "repository_eventrepository_add", "relation": "method", "confidence": "EXTRACTED", "source_file": "src/apps/event/repository.py", "source_location": "L22", "weight": 1.0}, {"source": "repository_eventrepository", "target": "repository_eventrepository_get_by_id_for_owner", "relation": "method", "confidence": "EXTRACTED", "source_file": "src/apps/event/repository.py", "source_location": "L25", "weight": 1.0}, {"source": "repository_eventrepository", "target": "repository_eventrepository_get_by_id", "relation": "method", "confidence": "EXTRACTED", "source_file": "src/apps/event/repository.py", "source_location": "L37", "weight": 1.0}, {"source": "repository_eventrepository", "target": "repository_eventrepository_get_by_id_for_update", "relation": "method", "confidence": "EXTRACTED", "source_file": "src/apps/event/repository.py", "source_location": "L42", "weight": 1.0}, {"source": "repository_eventrepository", "target": "repository_eventrepository_create_event_day", "relation": "method", "confidence": "EXTRACTED", "source_file": "src/apps/event/repository.py", "source_location": "L47", "weight": 1.0}, {"source": "repository_eventrepository", "target": "repository_eventrepository_get_event_day_for_owner", "relation": "method", "confidence": "EXTRACTED", "source_file": "src/apps/event/repository.py", "source_location": "L74", "weight": 1.0}, {"source": "repository_eventrepository", "target": "repository_eventrepository_get_event_day_by_id", "relation": "method", "confidence": "EXTRACTED", "source_file": "src/apps/event/repository.py", "source_location": "L87", "weight": 1.0}, {"source": "repository_eventrepository", "target": "repository_eventrepository_list_event_days", "relation": "method", "confidence": "EXTRACTED", "source_file": "src/apps/event/repository.py", "source_location": "L93", "weight": 1.0}, {"source": "repository_eventrepository", "target": "repository_eventrepository_delete_event_day", "relation": "method", "confidence": "EXTRACTED", "source_file": "src/apps/event/repository.py", "source_location": "L101", "weight": 1.0}, {"source": "repository_eventrepository", "target": "repository_eventrepository_count_event_days", "relation": "method", "confidence": "EXTRACTED", "source_file": "src/apps/event/repository.py", "source_location": "L111", "weight": 1.0}, {"source": "repository_eventrepository", "target": "repository_eventrepository_count_ticket_types", "relation": "method", "confidence": "EXTRACTED", "source_file": "src/apps/event/repository.py", "source_location": "L116", "weight": 1.0}, {"source": "repository_eventrepository", "target": "repository_eventrepository_count_ticket_allocations", "relation": "method", "confidence": "EXTRACTED", "source_file": "src/apps/event/repository.py", "source_location": "L121", "weight": 1.0}, {"source": "repository_eventrepository", "target": "repository_eventrepository_list_ticket_types", "relation": "method", "confidence": "EXTRACTED", "source_file": "src/apps/event/repository.py", "source_location": "L128", "weight": 1.0}, {"source": "repository_eventrepository", "target": "repository_eventrepository_list_allocations", "relation": "method", "confidence": "EXTRACTED", "source_file": "src/apps/event/repository.py", "source_location": "L136", "weight": 1.0}, {"source": "repository_eventrepository", "target": "repository_eventrepository_create_scan_status_history", "relation": "method", "confidence": "EXTRACTED", "source_file": "src/apps/event/repository.py", "source_location": "L145", "weight": 1.0}, {"source": "repository_eventrepository", "target": "repository_eventrepository_list_scan_status_history", "relation": "method", "confidence": "EXTRACTED", "source_file": "src/apps/event/repository.py", "source_location": "L165", "weight": 1.0}, {"source": "repository_eventrepository", "target": "repository_eventrepository_list_media_assets", "relation": "method", "confidence": "EXTRACTED", "source_file": "src/apps/event/repository.py", "source_location": "L175", "weight": 1.0}, {"source": "repository_eventrepository", "target": "repository_eventrepository_get_media_asset_by_id", "relation": "method", "confidence": "EXTRACTED", "source_file": "src/apps/event/repository.py", "source_location": "L193", "weight": 1.0}, {"source": "repository_eventrepository", "target": "repository_eventrepository_delete_media_asset", "relation": "method", "confidence": "EXTRACTED", "source_file": "src/apps/event/repository.py", "source_location": "L199", "weight": 1.0}, {"source": "repository_eventrepository", "target": "repository_eventrepository_get_interest_for_actor", "relation": "method", "confidence": "EXTRACTED", "source_file": "src/apps/event/repository.py", "source_location": "L204", "weight": 1.0}, {"source": "repository_eventrepository", "target": "repository_eventrepository_create_event_interest", "relation": "method", "confidence": "EXTRACTED", "source_file": "src/apps/event/repository.py", "source_location": "L217", "weight": 1.0}, {"source": "repository_eventrepository", "target": "repository_eventrepository_increment_event_interest_counter", "relation": "method", "confidence": "EXTRACTED", "source_file": "src/apps/event/repository.py", "source_location": "L237", "weight": 1.0}, {"source": "repository_eventrepository", "target": "repository_eventrepository_create_event_reseller", "relation": "method", "confidence": "EXTRACTED", "source_file": "src/apps/event/repository.py", "source_location": "L244", "weight": 1.0}, {"source": "repository_eventrepository", "target": "repository_eventrepository_get_reseller_for_event", "relation": "method", "confidence": "EXTRACTED", "source_file": "src/apps/event/repository.py", "source_location": "L264", "weight": 1.0}, {"source": "repository_eventrepository", "target": "repository_eventrepository_list_resellers_for_event", "relation": "method", "confidence": "EXTRACTED", "source_file": "src/apps/event/repository.py", "source_location": "L276", "weight": 1.0}, {"source": "repository_eventrepository", "target": "repository_eventrepository_list_reseller_invites_for_event", "relation": "method", "confidence": "EXTRACTED", "source_file": "src/apps/event/repository.py", "source_location": "L284", "weight": 1.0}, {"source": "repository_eventrepository", "target": "repository_eventrepository_list_published_events", "relation": "method", "confidence": "EXTRACTED", "source_file": "src/apps/event/repository.py", "source_location": "L307", "weight": 1.0}, {"source": "repository_eventrepository_create_event_day", "target": "repository_eventrepository_add", "relation": "calls", "confidence": "EXTRACTED", "source_file": "src/apps/event/repository.py", "source_location": "L69", "weight": 1.0}, {"source": "repository_eventrepository_create_scan_status_history", "target": "repository_eventrepository_add", "relation": "calls", "confidence": "EXTRACTED", "source_file": "src/apps/event/repository.py", "source_location": "L160", "weight": 1.0}, {"source": "repository_eventrepository_create_event_interest", "target": "repository_eventrepository_add", "relation": "calls", "confidence": "EXTRACTED", "source_file": "src/apps/event/repository.py", "source_location": "L232", "weight": 1.0}, {"source": "repository_eventrepository_create_event_reseller", "target": "repository_eventrepository_add", "relation": "calls", "confidence": "EXTRACTED", "source_file": "src/apps/event/repository.py", "source_location": "L259", "weight": 1.0}, {"source": "repository_rationale_88", "target": "repository_eventrepository_get_event_day_by_id", "relation": "rationale_for", "confidence": "EXTRACTED", "source_file": "src/apps/event/repository.py", "source_location": "L88", "weight": 1.0}, {"source": "repository_rationale_178", "target": "repository_eventrepository_list_media_assets", "relation": "rationale_for", "confidence": "EXTRACTED", "source_file": "src/apps/event/repository.py", "source_location": "L178", "weight": 1.0}, {"source": "repository_rationale_194", "target": "repository_eventrepository_get_media_asset_by_id", "relation": "rationale_for", "confidence": "EXTRACTED", "source_file": "src/apps/event/repository.py", "source_location": "L194", "weight": 1.0}, {"source": "repository_rationale_200", "target": "repository_eventrepository_delete_media_asset", "relation": "rationale_for", "confidence": "EXTRACTED", "source_file": "src/apps/event/repository.py", "source_location": "L200", "weight": 1.0}, {"source": "repository_rationale_291", "target": "repository_eventrepository_list_reseller_invites_for_event", "relation": "rationale_for", "confidence": "EXTRACTED", "source_file": "src/apps/event/repository.py", "source_location": "L291", "weight": 1.0}]}