{"nodes": [{"id": "12287d5104de", "label": "12287d5104de_.py", "file_type": "code", "source_file": "src/migrations/versions/12287d5104de_.py", "source_location": "L1"}, {"id": "12287d5104de_upgrade", "label": "upgrade()", "file_type": "code", "source_file": "src/migrations/versions/12287d5104de_.py", "source_location": "L19"}, {"id": "12287d5104de_downgrade", "label": "downgrade()", "file_type": "code", "source_file": "src/migrations/versions/12287d5104de_.py", "source_location": "L57"}, {"id": "12287d5104de_rationale_1", "label": "empty message  Revision ID: 12287d5104de Revises: 479742328475 Create Date: 2026", "file_type": "rationale", "source_file": "src/migrations/versions/12287d5104de_.py", "source_location": "L1"}], "edges": [{"source": "12287d5104de", "target": "alembic", "relation": "imports_from", "confidence": "EXTRACTED", "source_file": "src/migrations/versions/12287d5104de_.py", "source_location": "L8", "weight": 1.0}, {"source": "12287d5104de", "target": "sqlalchemy", "relation": "imports", "confidence": "EXTRACTED", "source_file": "src/migrations/versions/12287d5104de_.py", "source_location": "L9", "weight": 1.0}, {"source": "12287d5104de", "target": "sqlalchemy_dialects", "relation": "imports_from", "confidence": "EXTRACTED", "source_file": "src/migrations/versions/12287d5104de_.py", "source_location": "L10", "weight": 1.0}, {"source": "12287d5104de", "target": "12287d5104de_upgrade", "relation": "contains", "confidence": "EXTRACTED", "source_file": "src/migrations/versions/12287d5104de_.py", "source_location": "L19", "weight": 1.0}, {"source": "12287d5104de", "target": "12287d5104de_downgrade", "relation": "contains", "confidence": "EXTRACTED", "source_file": "src/migrations/versions/12287d5104de_.py", "source_location": "L57", "weight": 1.0}, {"source": "12287d5104de_rationale_1", "target": "12287d5104de", "relation": "rationale_for", "confidence": "EXTRACTED", "source_file": "src/migrations/versions/12287d5104de_.py", "source_location": "L1", "weight": 1.0}]}