{"nodes": [{"id": "models", "label": "models.py", "file_type": "code", "source_file": "src/apps/allocation/models.py", "source_location": "L1"}, {"id": "models_ticketholdermodel", "label": "TicketHolderModel", "file_type": "code", "source_file": "src/apps/allocation/models.py", "source_location": "L25"}, {"id": "base", "label": "Base", "file_type": "code", "source_file": "", "source_location": ""}, {"id": "uuidprimarykeymixin", "label": "UUIDPrimaryKeyMixin", "file_type": "code", "source_file": "", "source_location": ""}, {"id": "timestampmixin", "label": "TimeStampMixin", "file_type": "code", "source_file": "", "source_location": ""}, {"id": "models_claimlinkmodel", "label": "ClaimLinkModel", "file_type": "code", "source_file": "src/apps/allocation/models.py", "source_location": "L48"}, {"id": "models_revokedscantokenmodel", "label": "RevokedScanTokenModel", "file_type": "code", "source_file": "src/apps/allocation/models.py", "source_location": "L83"}, {"id": "models_allocationmodel", "label": "AllocationModel", "file_type": "code", "source_file": "src/apps/allocation/models.py", "source_location": "L100"}, {"id": "models_allocationticketmodel", "label": "AllocationTicketModel", "file_type": "code", "source_file": "src/apps/allocation/models.py", "source_location": "L134"}, {"id": "models_allocationedgemodel", "label": "AllocationEdgeModel", "file_type": "code", "source_file": "src/apps/allocation/models.py", "source_location": "L145"}, {"id": "models_ordermodel", "label": "OrderModel", "file_type": "code", "source_file": "src/apps/allocation/models.py", "source_location": "L168"}, {"id": "models_rationale_169", "label": "Order model \u2014 created for every allocation (PURCHASE or TRANSFER).     Free tran", "file_type": "rationale", "source_file": "src/apps/allocation/models.py", "source_location": "L169"}], "edges": [{"source": "models", "target": "uuid", "relation": "imports", "confidence": "EXTRACTED", "source_file": "src/apps/allocation/models.py", "source_location": "L1", "weight": 1.0}, {"source": "models", "target": "datetime", "relation": "imports_from", "confidence": "EXTRACTED", "source_file": "src/apps/allocation/models.py", "source_location": "L2", "weight": 1.0}, {"source": "models", "target": "sqlalchemy", "relation": "imports_from", "confidence": "EXTRACTED", "source_file": "src/apps/allocation/models.py", "source_location": "L4", "weight": 1.0}, {"source": "models", "target": "sqlalchemy_dialects_postgresql", "relation": "imports_from", "confidence": "EXTRACTED", "source_file": "src/apps/allocation/models.py", "source_location": "L17", "weight": 1.0}, {"source": "models", "target": "sqlalchemy_orm", "relation": "imports_from", "confidence": "EXTRACTED", "source_file": "src/apps/allocation/models.py", "source_location": "L18", "weight": 1.0}, {"source": "models", "target": "db_base", "relation": "imports_from", "confidence": "EXTRACTED", "source_file": "src/apps/allocation/models.py", "source_location": "L20", "weight": 1.0}, {"source": "models", "target": "apps_ticketing_enums", "relation": "imports_from", "confidence": "EXTRACTED", "source_file": "src/apps/allocation/models.py", "source_location": "L21", "weight": 1.0}, {"source": "models", "target": "enums", "relation": "imports_from", "confidence": "EXTRACTED", "source_file": "src/apps/allocation/models.py", "source_location": "L22", "weight": 1.0}, {"source": "models", "target": "models_ticketholdermodel", "relation": "contains", "confidence": "EXTRACTED", "source_file": "src/apps/allocation/models.py", "source_location": "L25", "weight": 1.0}, {"source": "models_ticketholdermodel", "target": "base", "relation": "inherits", "confidence": "EXTRACTED", "source_file": "src/apps/allocation/models.py", "source_location": "L25", "weight": 1.0}, {"source": "models_ticketholdermodel", "target": "uuidprimarykeymixin", "relation": "inherits", "confidence": "EXTRACTED", "source_file": "src/apps/allocation/models.py", "source_location": "L25", "weight": 1.0}, {"source": "models_ticketholdermodel", "target": "timestampmixin", "relation": "inherits", "confidence": "EXTRACTED", "source_file": "src/apps/allocation/models.py", "source_location": "L25", "weight": 1.0}, {"source": "models", "target": "models_claimlinkmodel", "relation": "contains", "confidence": "EXTRACTED", "source_file": "src/apps/allocation/models.py", "source_location": "L48", "weight": 1.0}, {"source": "models_claimlinkmodel", "target": "base", "relation": "inherits", "confidence": "EXTRACTED", "source_file": "src/apps/allocation/models.py", "source_location": "L48", "weight": 1.0}, {"source": "models_claimlinkmodel", "target": "uuidprimarykeymixin", "relation": "inherits", "confidence": "EXTRACTED", "source_file": "src/apps/allocation/models.py", "source_location": "L48", "weight": 1.0}, {"source": "models_claimlinkmodel", "target": "timestampmixin", "relation": "inherits", "confidence": "EXTRACTED", "source_file": "src/apps/allocation/models.py", "source_location": "L48", "weight": 1.0}, {"source": "models", "target": "models_revokedscantokenmodel", "relation": "contains", "confidence": "EXTRACTED", "source_file": "src/apps/allocation/models.py", "source_location": "L83", "weight": 1.0}, {"source": "models_revokedscantokenmodel", "target": "base", "relation": "inherits", "confidence": "EXTRACTED", "source_file": "src/apps/allocation/models.py", "source_location": "L83", "weight": 1.0}, {"source": "models_revokedscantokenmodel", "target": "uuidprimarykeymixin", "relation": "inherits", "confidence": "EXTRACTED", "source_file": "src/apps/allocation/models.py", "source_location": "L83", "weight": 1.0}, {"source": "models", "target": "models_allocationmodel", "relation": "contains", "confidence": "EXTRACTED", "source_file": "src/apps/allocation/models.py", "source_location": "L100", "weight": 1.0}, {"source": "models_allocationmodel", "target": "base", "relation": "inherits", "confidence": "EXTRACTED", "source_file": "src/apps/allocation/models.py", "source_location": "L100", "weight": 1.0}, {"source": "models_allocationmodel", "target": "uuidprimarykeymixin", "relation": "inherits", "confidence": "EXTRACTED", "source_file": "src/apps/allocation/models.py", "source_location": "L100", "weight": 1.0}, {"source": "models_allocationmodel", "target": "timestampmixin", "relation": "inherits", "confidence": "EXTRACTED", "source_file": "src/apps/allocation/models.py", "source_location": "L100", "weight": 1.0}, {"source": "models", "target": "models_allocationticketmodel", "relation": "contains", "confidence": "EXTRACTED", "source_file": "src/apps/allocation/models.py", "source_location": "L134", "weight": 1.0}, {"source": "models_allocationticketmodel", "target": "base", "relation": "inherits", "confidence": "EXTRACTED", "source_file": "src/apps/allocation/models.py", "source_location": "L134", "weight": 1.0}, {"source": "models_allocationticketmodel", "target": "timestampmixin", "relation": "inherits", "confidence": "EXTRACTED", "source_file": "src/apps/allocation/models.py", "source_location": "L134", "weight": 1.0}, {"source": "models", "target": "models_allocationedgemodel", "relation": "contains", "confidence": "EXTRACTED", "source_file": "src/apps/allocation/models.py", "source_location": "L145", "weight": 1.0}, {"source": "models_allocationedgemodel", "target": "base", "relation": "inherits", "confidence": "EXTRACTED", "source_file": "src/apps/allocation/models.py", "source_location": "L145", "weight": 1.0}, {"source": "models_allocationedgemodel", "target": "uuidprimarykeymixin", "relation": "inherits", "confidence": "EXTRACTED", "source_file": "src/apps/allocation/models.py", "source_location": "L145", "weight": 1.0}, {"source": "models_allocationedgemodel", "target": "timestampmixin", "relation": "inherits", "confidence": "EXTRACTED", "source_file": "src/apps/allocation/models.py", "source_location": "L145", "weight": 1.0}, {"source": "models", "target": "models_ordermodel", "relation": "contains", "confidence": "EXTRACTED", "source_file": "src/apps/allocation/models.py", "source_location": "L168", "weight": 1.0}, {"source": "models_ordermodel", "target": "base", "relation": "inherits", "confidence": "EXTRACTED", "source_file": "src/apps/allocation/models.py", "source_location": "L168", "weight": 1.0}, {"source": "models_ordermodel", "target": "uuidprimarykeymixin", "relation": "inherits", "confidence": "EXTRACTED", "source_file": "src/apps/allocation/models.py", "source_location": "L168", "weight": 1.0}, {"source": "models_ordermodel", "target": "timestampmixin", "relation": "inherits", "confidence": "EXTRACTED", "source_file": "src/apps/allocation/models.py", "source_location": "L168", "weight": 1.0}, {"source": "models_rationale_169", "target": "models_ordermodel", "relation": "rationale_for", "confidence": "EXTRACTED", "source_file": "src/apps/allocation/models.py", "source_location": "L169", "weight": 1.0}]}